unboxer/__init__.py
unboxer/cldf.py
unboxer/cli.py
unboxer/data/interlinear_config.yaml
unboxer/data/shoebox.yaml
unboxer/data/toolbox.yaml
unboxer/helpers.py
unboxer-0.1.1.dist-info/LICENSE
unboxer-0.1.1.dist-info/METADATA
unboxer-0.1.1.dist-info/WHEEL
unboxer-0.1.1.dist-info/entry_points.txt
unboxer-0.1.1.dist-info/RECORD
